README
setup.py
oldowan/__init__.py
oldowan.mitomotifs.egg-info/PKG-INFO
oldowan.mitomotifs.egg-info/SOURCES.txt
oldowan.mitomotifs.egg-info/dependency_links.txt
oldowan.mitomotifs.egg-info/namespace_packages.txt
oldowan.mitomotifs.egg-info/top_level.txt
oldowan.mitomotifs.egg-info/zip-safe
oldowan/mitomotifs/__init__.py
oldowan/mitomotifs/mitomap_data.py
oldowan/mitomotifs/polymorphism.py
oldowan/mitomotifs/rCRS.py
oldowan/mitomotifs/reduction_funcs.py
oldowan/mitomotifs/seq2sites.py
oldowan/mitomotifs/sites2seq.py
oldowan/mitomotifs/sites2str.py
oldowan/mitomotifs/str2sites.py
oldowan/mitomotifs/biopython/__init__.py
oldowan/mitomotifs/biopython/listfns.py
oldowan/mitomotifs/biopython/pairwise2.py
