Metadata-Version: 1.0
Name: oldowan.mitomotifs
Version: 1.0.2
Summary: Transform human mtDNA sequence to variant sites and vice versa.
